elefantolib_events/__init__.py
elefantolib_events/emitter.py
elefantolib_events/listener.py
elefantolib_events-0.6.1.dist-info/LICENSE
elefantolib_events-0.6.1.dist-info/METADATA
elefantolib_events-0.6.1.dist-info/WHEEL
elefantolib_events-0.6.1.dist-info/RECORD
